{
  "nav": [
    {
      "nav_name": "How It Works",
      "link": "/how-it-works",
      "type": "",
      "full_width": false,
      "sub_nav": []
    },
    {
      "nav_name": "Core of QUDEX",
      "link": "/core-of-qudex",
      "type": "",
      "full_width": false,
      "sub_nav": [
        {
          "nav_name": "Step 1",
          "link": "/how-it-works/step-1"
        },
        {
          "nav_name": "Step 2",
          "link": "/how-it-works/step-2"
        },
        {
          "nav_name": "Step 3",
          "link": "/how-it-works/step-3"
        }
      ]
    },
    {
      "nav_name": "The Platform",
      "link": "/the-platform",
      "type": "",
      "sub_nav": []
    },
    {
      "nav_name": "Use Cases",
      "link": "/use-cases",
      "type": "",
      "sub_nav": []
    },
    {
      "nav_name": "Eco Score Card",
      "link": "/eco-score-card",
      "type": "",
      "sub_nav": []
    },
    {
      "nav_name": "What Is QUDE™",
      "link": "/what-is-qudex",
      "type": "",
      "sub_nav": []
    },
    {
      "nav_name": "Land Partner",
      "link": "/land-partner",
      "type": "",
      "sub_nav": []
    }
  ]
}
